accelbyte_py_sdk/api/match2/__init__.py
accelbyte_py_sdk/api/match2/errors.py
accelbyte_py_sdk/api/match2/models/__init__.py
accelbyte_py_sdk/api/match2/models/api_back_fill_accept_request.py
accelbyte_py_sdk/api/match2/models/api_back_fill_create_request.py
accelbyte_py_sdk/api/match2/models/api_back_fill_reject_request.py
accelbyte_py_sdk/api/match2/models/api_backfill_create_response.py
accelbyte_py_sdk/api/match2/models/api_backfill_get_response.py
accelbyte_py_sdk/api/match2/models/api_backfill_proposal_response.py
accelbyte_py_sdk/api/match2/models/api_external_failure_metric_record.py
accelbyte_py_sdk/api/match2/models/api_list_backfill_query_response.py
accelbyte_py_sdk/api/match2/models/api_list_environment_variables_response.py
accelbyte_py_sdk/api/match2/models/api_list_match_functions_response.py
accelbyte_py_sdk/api/match2/models/api_list_match_pool_tickets_response.py
accelbyte_py_sdk/api/match2/models/api_list_match_pools_response.py
accelbyte_py_sdk/api/match2/models/api_list_rule_sets_response.py
accelbyte_py_sdk/api/match2/models/api_match.py
accelbyte_py_sdk/api/match2/models/api_match_function_config.py
accelbyte_py_sdk/api/match2/models/api_match_function_override.py
accelbyte_py_sdk/api/match2/models/api_match_function_request.py
accelbyte_py_sdk/api/match2/models/api_match_pool.py
accelbyte_py_sdk/api/match2/models/api_match_pool_config.py
accelbyte_py_sdk/api/match2/models/api_match_rule_set_name_data.py
accelbyte_py_sdk/api/match2/models/api_match_ticket_request.py
accelbyte_py_sdk/api/match2/models/api_match_ticket_response.py
accelbyte_py_sdk/api/match2/models/api_match_ticket_status.py
accelbyte_py_sdk/api/match2/models/api_match_ticket_statuses.py
accelbyte_py_sdk/api/match2/models/api_namespace_config_list.py
accelbyte_py_sdk/api/match2/models/api_party.py
accelbyte_py_sdk/api/match2/models/api_patch_namespace_config_request.py
accelbyte_py_sdk/api/match2/models/api_player_data.py
accelbyte_py_sdk_service_match2-0.23.0.dist-info/METADATA
accelbyte_py_sdk_service_match2-0.23.0.dist-info/WHEEL
accelbyte_py_sdk_service_match2-0.23.0.dist-info/top_level.txt
accelbyte_py_sdk_service_match2-0.23.0.dist-info/RECORD
